{
  "gitSyncId": "6765269cfe58806da85dee0c_f754daf5-3fba-47a8-a561-b1ccc7681fb4",
  "id": "Capture Sheep Detail_jsUpdateSheep.validateAndUpdateSheep",
  "pluginId": "js-plugin",
  "pluginType": "JS",
  "unpublishedAction": {
    "actionConfiguration": {
      "encodeParamsToggle": true,
      "jsArguments": [],
      "paginationType": "NONE",
      "timeoutInMillisecond": 10000
    },
    "collectionId": "Capture Sheep Detail_jsUpdateSheep",
    "confirmBeforeExecute": false,
    "datasource": {
      "isAutoGenerated": false,
      "name": "UNUSED_DATASOURCE",
      "pluginId": "js-plugin"
    },
    "dynamicBindingPathList": [
      {
        "key": "body"
      }
    ],
    "executeOnLoad": false,
    "fullyQualifiedName": "jsUpdateSheep.validateAndUpdateSheep",
    "name": "validateAndUpdateSheep",
    "pageId": "Capture Sheep Detail",
    "userSetOnLoad": false
  }
}