{
  "accentColor": "{{appsmith.theme.colors.primaryColor}}",
  "allowCurrencyChange": false,
  "animateLoading": true,
  "autoFocus": false,
  "borderRadius": "{{appsmith.theme.borderRadius.appBorderRadius}}",
  "bottomRow": 22,
  "boxShadow": "none",
  "decimals": 2,
  "defaultCurrencyCode": "ZAR",
  "defaultText": "{{\n  (\n    Number(inpIndDosage.text || 0) *\n    Number(inpMedUnitCost.text || 0)\n  ).toFixed(2)\n}}\n",
  "dynamicBindingPathList": [
    {
      "key": "accentColor"
    },
    {
      "key": "borderRadius"
    },
    {
      "key": "defaultText"
    }
  ],
  "dynamicHeight": "FIXED",
  "dynamicTriggerPathList": [],
  "iconAlign": "left",
  "isDisabled": false,
  "isLoading": false,
  "isRequired": false,
  "isVisible": true,
  "key": "fvjtx6gwv7",
  "label": "Dosage Cost",
  "labelAlignment": "left",
  "labelPosition": "Top",
  "labelStyle": "",
  "labelTextSize": "0.875rem",
  "labelWidth": 5,
  "leftColumn": 44,
  "maxDynamicHeight": 9000,
  "minDynamicHeight": 4,
  "minWidth": 450,
  "mobileBottomRow": 22,
  "mobileLeftColumn": 44,
  "mobileRightColumn": 64,
  "mobileTopRow": 15,
  "needsErrorInfo": false,
  "parentColumnSpace": 16.8125,
  "parentId": "tkdg3agm3w",
  "parentRowSpace": 10,
  "renderMode": "CANVAS",
  "resetOnSubmit": true,
  "responsiveBehavior": "fill",
  "rightColumn": 64,
  "showStepArrows": false,
  "topRow": 15,
  "type": "CURRENCY_INPUT_WIDGET",
  "version": 1,
  "widgetId": "uzmqk1exe0",
  "widgetName": "inpDosageCost"
}