{
  "gitSyncId": "6765269cfe58806da85dee0c_3ac4b022-0620-48e3-a669-9d6dfe24bfe2",
  "id": "Death Reason Detail_fetchDeathReason",
  "pluginId": "postgres-plugin",
  "pluginType": "DB",
  "unpublishedAction": {
    "actionConfiguration": {
      "body": "SELECT * FROM \"DEATH_REASONS\" ORDER by \"DeathReasonID\";\n",
      "encodeParamsToggle": true,
      "paginationType": "NONE",
      "pluginSpecifiedTemplates": [
        {
          "value": true
        }
      ],
      "timeoutInMillisecond": 10000
    },
    "confirmBeforeExecute": false,
    "datasource": {
      "id": "SheepFarmDB",
      "isAutoGenerated": false,
      "name": "SheepFarmDB",
      "pluginId": "postgres-plugin"
    },
    "dynamicBindingPathList": [],
    "executeOnLoad": true,
    "name": "fetchDeathReason",
    "pageId": "Death Reason Detail",
    "userSetOnLoad": false
  }
}